<Properties StartupConfiguration="{B4390284-04FB-4802-AA46-57A02E63339D}|https">
  <MonoDevelop.Ide.DebuggingService.PinnedWatches />
  <MonoDevelop.Ide.Workbench ActiveDocument="MyNeighborhood/Pages/FetchData.razor">
    <Files>
      <File FileName="MyNeighborhood/Pages/Counter.razor" />
      <File FileName="MyNeighborhood/Pages/FetchData.razor" Line="1" Column="1" />
    </Files>
    <Pads>
      <Pad Id="ProjectPad">
        <State name="__root__">
          <Node name="MyNeighborhood" expanded="True">
            <Node name="MyNeighborhood" expanded="True">
              <Node name="Data" expanded="True" />
              <Node name="Pages" expanded="True" />
              <Node name="wwwroot" expanded="True">
                <Node name="css" expanded="True" />
              </Node>
            </Node>
          </Node>
        </State>
      </Pad>
    </Pads>
  </MonoDevelop.Ide.Workbench>
  <MultiItemStartupConfigurations />
  <MonoDevelop.Ide.Workspace ActiveConfiguration="Debug" />
  <MonoDevelop.Ide.ItemProperties.MyNeighborhood PreferredExecutionTarget="/Applications/Google Chrome.app" />
  <MonoDevelop.Ide.DebuggingService.Breakpoints>
    <BreakpointStore />
  </MonoDevelop.Ide.DebuggingService.Breakpoints>
</Properties>